anprx/__init__.py
anprx/animate.py
anprx/constants.py
anprx/core.py
anprx/helpers.py
anprx/nominatim.py
anprx/plot.py
anprx/utils.py
anprx-0.1.2.dist-info/METADATA
anprx-0.1.2.dist-info/RECORD
anprx-0.1.2.dist-info/WHEEL
anprx-0.1.2.dist-info/top_level.txt
